jmpui-0.1.22.dist-info/licenses/LICENSE
pig_ui/__init__.py
pig_ui/app.py
pig_ui/constants.py
pig_ui/events.py
pig_ui/modules.py
pig_ui/ui/bezier.py
pig_ui/ui/constants.py
pig_ui/ui/ui_colorpicker.py
pig_ui/ui/ui_dropdown.py
pig_ui/ui/ui_element.py
pig_ui/ui/ui_manager.py
pig_ui/ui/ui_menu.py
pig_ui/ui/ui_sidebar.py
pig_ui/ui/ui_spinbox.py
pig_ui/ui/ui_textinput.py
pig_ui/ui/ux_element.py
jmpui-0.1.22.dist-info/METADATA
jmpui-0.1.22.dist-info/WHEEL
jmpui-0.1.22.dist-info/top_level.txt
jmpui-0.1.22.dist-info/RECORD
