Metadata-Version: 2.4
Name: jmpUI
Version: 0.1.22
Summary: A Framework for Pygame UI Elements
Author-email: Justus Decker <justus.d2025@gmail.com>
License:                     GNU GENERAL PUBLIC LICENSE
Project-URL: homepage, https://github.com/justusdecker/pigUI
Requires-Python: >=3.8
License-File: LICENSE
Requires-Dist: pygame
Requires-Dist: numpy
Dynamic: license-file
